{
    "usuarios":[
    {
    "nick":"betebetoven",
    "password":"jaja",
    "monedas":"100",
    "edad":"32"
    },
    {
    "nick":"sofiaruano",
    "password":"Blaancamagy",
    "monedas":"10000",
    "edad":"22"
    },
    {
    "nick":"colosho",
    "password":"colosho",
    "monedas":"0",
    "edad":"2"
    }
    ],
    "articulos":[
    {
    "id":"0",
    "categoria":"Legendario",
    "precio":"12",
    "nombre":"M13",
    "src":"e"
    },
    {
    "id":"1",
    "categoria":"Epico",
    "precio":"23",
    "nombre":"Mac",
    "src":"e"
    },
    {
    "id":"2",
    "categoria":"Raro",
    "precio":"56",
    "nombre":"Mimilona",
    "src":"e"
    }
    ],
    "tutorial":{
    "ancho":"10",
    "alto":"20",
    "movimientos":[
    {
    "x":"1",
    "y":"2"
    },
    {
    "x":"3",
    "y":"4"
    },
    {
    "x":"5",
    "y":"6"
    }
    ]
    }
    }